termmenu/__init__.py
termmenu/termmenu.py
termmenu-2.0.1.dist-info/LICENSE.txt
termmenu-2.0.1.dist-info/METADATA
termmenu-2.0.1.dist-info/WHEEL
termmenu-2.0.1.dist-info/top_level.txt
termmenu-2.0.1.dist-info/RECORD
