Metadata-Version: 2.1
Name: termmenu
Version: 2.0.1
Summary: A tool for making terminal menus.
Home-page: https://github.com/dnorhoj/termmenu
Author: dnorhoj
Author-email: daniel.norhoj@gmail.com
License: UNKNOWN
Platform: UNKNOWN
Classifier: Programming Language :: Python :: 3
Classifier: License :: OSI Approved :: MIT License
Classifier: Operating System :: OS Independent
